wzarp/CityWeather.py
wzarp/__init__.py
wzarp-0.0.4.dist-info/METADATA
wzarp-0.0.4.dist-info/WHEEL
wzarp-0.0.4.dist-info/top_level.txt
wzarp-0.0.4.dist-info/RECORD
