Metadata-Version: 2.1
Name: wzarp
Version: 0.0.4
Summary: Wzarp is a Weather library
Home-page: https://github.com/Falangizzle/wzarp
Author: Marunov V.A.
Author-email: marunov02@mail.ru
License: UNKNOWN
Platform: any
Requires-Python: >=3.7
Requires-Dist: requests (>=2.25.1)
Requires-Dist: beautifulsoup4
